{
  "changed": [
    {
      "Id": 8094015,
      "RevitName": "物流中心 南、北側立面索引圖",
      "CurrentNumber": "ARB-D03001",
      "TargetNumber": "ARB-D02078"
    },
    {
      "Id": 8094051,
      "RevitName": "物流中心 南側立面圖(1/2)",
      "CurrentNumber": "ARB-D03002",
      "TargetNumber": "ARB-D02079"
    },
    {
      "Id": 8094057,
      "RevitName": "物流中心 南側立面圖(2/2)",
      "CurrentNumber": "ARB-D03003",
      "TargetNumber": "ARB-D02080"
    },
    {
      "Id": 8094027,
      "RevitName": "物流中心 北側立面圖(1/2)",
      "CurrentNumber": "ARB-D03004",
      "TargetNumber": "ARB-D02081"
    },
    {
      "Id": 8094033,
      "RevitName": "物流中心 北側立面圖(2/2)",
      "CurrentNumber": "ARB-D03005",
      "TargetNumber": "ARB-D02082"
    },
    {
      "Id": 9317927,
      "RevitName": "物流中心 東側立面圖",
      "CurrentNumber": "ARB-D03006",
      "TargetNumber": "ARB-D02083"
    },
    {
      "Id": 10548528,
      "RevitName": "物流中心 西側立面圖",
      "CurrentNumber": "ARB-D03007",
      "TargetNumber": "ARB-D02084"
    },
    {
      "Id": 8094159,
      "RevitName": "物流中心 甲安全梯詳圖(一)",
      "CurrentNumber": "ARB-D05001",
      "TargetNumber": "ARB-D04016"
    },
    {
      "Id": 8094171,
      "RevitName": "物流中心 乙安全梯詳圖(一)",
      "CurrentNumber": "ARB-D05002",
      "TargetNumber": "ARB-D04017"
    },
    {
      "Id": 8094177,
      "RevitName": "物流中心 甲、乙安全梯詳圖(二)",
      "CurrentNumber": "ARB-D05003",
      "TargetNumber": "ARB-D04018"
    },
    {
      "Id": 8094195,
      "RevitName": "物流中心 丁安全梯詳圖(一)",
      "CurrentNumber": "ARB-D05006",
      "TargetNumber": "ARB-D04021"
    },
    {
      "Id": 8094207,
      "RevitName": "物流中心 戊安全梯詳圖(一)",
      "CurrentNumber": "ARB-D05007",
      "TargetNumber": "ARB-D04022"
    },
    {
      "Id": 8094213,
      "RevitName": "物流中心 丁、戊安全梯詳圖(二)",
      "CurrentNumber": "ARB-D05008",
      "TargetNumber": "ARB-D04023"
    },
    {
      "Id": 8105411,
      "RevitName": "物流中心 廁所詳圖(一)",
      "CurrentNumber": "ARB-D05013",
      "TargetNumber": "ARB-D04028"
    },
    {
      "Id": 8094249,
      "RevitName": "物流中心 廁所詳圖(二)",
      "CurrentNumber": "ARB-D05014",
      "TargetNumber": "ARB-D04029"
    },
    {
      "Id": 8094243,
      "RevitName": "物流中心 廁所詳圖(三)",
      "CurrentNumber": "ARB-D05015",
      "TargetNumber": "ARB-D04030"
    },
    {
      "Id": 9391418,
      "RevitName": "物流中心 地下車道平面索引圖",
      "CurrentNumber": "ARB-D05016",
      "TargetNumber": "ARB-D04031"
    },
    {
      "Id": 9579023,
      "RevitName": "物流中心 地下車道平面詳圖(1/2)",
      "CurrentNumber": "ARB-D05017",
      "TargetNumber": "ARB-D04032"
    },
    {
      "Id": 9579085,
      "RevitName": "物流中心 地下車道平面詳圖(2/2)",
      "CurrentNumber": "ARB-D05018",
      "TargetNumber": "ARB-D04033"
    },
    {
      "Id": 11035453,
      "RevitName": "物流中心 地下室雨水貯集池A詳圖",
      "CurrentNumber": "ARB-D05023",
      "TargetNumber": "ARB-D04038"
    },
    {
      "Id": 11031417,
      "RevitName": "物流中心 地下室雨水貯集池B詳圖",
      "CurrentNumber": "ARB-D05024",
      "TargetNumber": "ARB-D04039"
    },
    {
      "Id": 8094357,
      "RevitName": "物流中心 FRP水箱詳圖",
      "CurrentNumber": "ARB-D05027",
      "TargetNumber": "ARB-D04042"
    },
    {
      "Id": 8094147,
      "RevitName": "物流中心 地下層雨水回收、自來水及消防水箱詳圖",
      "CurrentNumber": "ARB-D05028",
      "TargetNumber": "ARB-D04043"
    },
    {
      "Id": 8094153,
      "RevitName": "物流中心 屋頂層自來水及消防水箱詳圖",
      "CurrentNumber": "ARB-D05029",
      "TargetNumber": "ARB-D04044"
    },
    {
      "Id": 8093865,
      "RevitName": "物流中心 一層天花平面圖(1/8)",
      "CurrentNumber": "ARB-D07063",
      "TargetNumber": "ARB-D07062"
    },
    {
      "Id": 8093871,
      "RevitName": "物流中心 一層天花平面圖(2/8)",
      "CurrentNumber": "ARB-D07064",
      "TargetNumber": "ARB-D07063"
    },
    {
      "Id": 8241067,
      "RevitName": "物流中心 一層天花平面圖(3/8)",
      "CurrentNumber": "ARB-D07065",
      "TargetNumber": "ARB-D07064"
    },
    {
      "Id": 11639369,
      "RevitName": "物流中心 一層天花平面圖(4/8)",
      "CurrentNumber": "ARB-D07066",
      "TargetNumber": "ARB-D07065"
    },
    {
      "Id": 11639375,
      "RevitName": "物流中心 一層天花平面圖(5/8)",
      "CurrentNumber": "ARB-D07067",
      "TargetNumber": "ARB-D07066"
    },
    {
      "Id": 11639381,
      "RevitName": "物流中心 一層天花平面圖(6/8)",
      "CurrentNumber": "ARB-D07068",
      "TargetNumber": "ARB-D07067"
    },
    {
      "Id": 11639387,
      "RevitName": "物流中心 一層天花平面圖(7/8)",
      "CurrentNumber": "ARB-D07069",
      "TargetNumber": "ARB-D07068"
    },
    {
      "Id": 11639393,
      "RevitName": "物流中心 一層天花平面圖(8/8)",
      "CurrentNumber": "ARB-D07070",
      "TargetNumber": "ARB-D07069"
    },
    {
      "Id": 9503706,
      "RevitName": "物流中心 二層天花平面圖(1/8)",
      "CurrentNumber": "ARB-D07071",
      "TargetNumber": "ARB-D07070"
    },
    {
      "Id": 9503713,
      "RevitName": "物流中心 二層天花平面圖(2/8)",
      "CurrentNumber": "ARB-D07072",
      "TargetNumber": "ARB-D07071"
    },
    {
      "Id": 9503720,
      "RevitName": "物流中心 二層天花平面圖(3/8)",
      "CurrentNumber": "ARB-D07073",
      "TargetNumber": "ARB-D07072"
    },
    {
      "Id": 11640199,
      "RevitName": "物流中心 二層天花平面圖(4/8)",
      "CurrentNumber": "ARB-D07074",
      "TargetNumber": "ARB-D07073"
    },
    {
      "Id": 11640205,
      "RevitName": "物流中心 二層天花平面圖(5/8)",
      "CurrentNumber": "ARB-D07075",
      "TargetNumber": "ARB-D07074"
    },
    {
      "Id": 11640211,
      "RevitName": "物流中心 二層天花平面圖(6/8)",
      "CurrentNumber": "ARB-D07076",
      "TargetNumber": "ARB-D07075"
    },
    {
      "Id": 11640217,
      "RevitName": "物流中心 二層天花平面圖(7/8)",
      "CurrentNumber": "ARB-D07077",
      "TargetNumber": "ARB-D07076"
    },
    {
      "Id": 11640223,
      "RevitName": "物流中心 二層天花平面圖(8/8)",
      "CurrentNumber": "ARB-D07078",
      "TargetNumber": "ARB-D07077"
    },
    {
      "Id": 11654393,
      "RevitName": "物流中心 三層天花平面圖(1/8)",
      "CurrentNumber": "ARB-D07079",
      "TargetNumber": "ARB-D07078"
    },
    {
      "Id": 11655361,
      "RevitName": "物流中心 三層天花平面圖(2/8)",
      "CurrentNumber": "ARB-D07080",
      "TargetNumber": "ARB-D07079"
    },
    {
      "Id": 11655579,
      "RevitName": "物流中心 三層天花平面圖(3/8)",
      "CurrentNumber": "ARB-D07081",
      "TargetNumber": "ARB-D07080"
    },
    {
      "Id": 11656663,
      "RevitName": "物流中心 三層天花平面圖(4/8)",
      "CurrentNumber": "ARB-D07082",
      "TargetNumber": "ARB-D07081"
    },
    {
      "Id": 11657609,
      "RevitName": "物流中心 三層天花平面圖(5/8)",
      "CurrentNumber": "ARB-D07083",
      "TargetNumber": "ARB-D07082"
    },
    {
      "Id": 11658200,
      "RevitName": "物流中心 三層天花平面圖(6/8)",
      "CurrentNumber": "ARB-D07084",
      "TargetNumber": "ARB-D07083"
    },
    {
      "Id": 11658700,
      "RevitName": "物流中心 三層天花平面圖(7/8)",
      "CurrentNumber": "ARB-D07085",
      "TargetNumber": "ARB-D07084"
    },
    {
      "Id": 11659319,
      "RevitName": "物流中心 三層天花平面圖(8/8)",
      "CurrentNumber": "ARB-D07086",
      "TargetNumber": "ARB-D07085"
    },
    {
      "Id": 11645797,
      "RevitName": "物流中心 四層天花平面圖(1/8)",
      "CurrentNumber": "ARB-D07087",
      "TargetNumber": "ARB-D07086"
    },
    {
      "Id": 11647007,
      "RevitName": "物流中心 四層天花平面圖(2/8)",
      "CurrentNumber": "ARB-D07088",
      "TargetNumber": "ARB-D07087"
    },
    {
      "Id": 11647330,
      "RevitName": "物流中心 四層天花平面圖(3/8)",
      "CurrentNumber": "ARB-D07089",
      "TargetNumber": "ARB-D07088"
    },
    {
      "Id": 11647729,
      "RevitName": "物流中心 四層天花平面圖(4/8)",
      "CurrentNumber": "ARB-D07090",
      "TargetNumber": "ARB-D07089"
    },
    {
      "Id": 11649860,
      "RevitName": "物流中心 四層天花平面圖(5/8)",
      "CurrentNumber": "ARB-D07091",
      "TargetNumber": "ARB-D07090"
    },
    {
      "Id": 11650760,
      "RevitName": "物流中心 四層天花平面圖(6/8)",
      "CurrentNumber": "ARB-D07092",
      "TargetNumber": "ARB-D07091"
    },
    {
      "Id": 11651213,
      "RevitName": "物流中心 四層天花平面圖(7/8)",
      "CurrentNumber": "ARB-D07093",
      "TargetNumber": "ARB-D07092"
    },
    {
      "Id": 11652807,
      "RevitName": "物流中心 四層天花平面圖(8/8)",
      "CurrentNumber": "ARB-D07094",
      "TargetNumber": "ARB-D07093"
    },
    {
      "Id": 11643539,
      "RevitName": "物流中心 五層天花平面圖(1/8)",
      "CurrentNumber": "ARB-D07095",
      "TargetNumber": "ARB-D07094"
    },
    {
      "Id": 11643765,
      "RevitName": "物流中心 五層天花平面圖(2/8)",
      "CurrentNumber": "ARB-D07096",
      "TargetNumber": "ARB-D07095"
    },
    {
      "Id": 11643782,
      "RevitName": "物流中心 五層天花平面圖(3/8)",
      "CurrentNumber": "ARB-D07097",
      "TargetNumber": "ARB-D07096"
    },
    {
      "Id": 11643795,
      "RevitName": "物流中心 五層天花平面圖(4/8)",
      "CurrentNumber": "ARB-D07098",
      "TargetNumber": "ARB-D07097"
    },
    {
      "Id": 11643909,
      "RevitName": "物流中心 五層天花平面圖(5/8)",
      "CurrentNumber": "ARB-D07099",
      "TargetNumber": "ARB-D07098"
    },
    {
      "Id": 11644283,
      "RevitName": "物流中心 五層天花平面圖(6/8)",
      "CurrentNumber": "ARB-D07100",
      "TargetNumber": "ARB-D07099"
    },
    {
      "Id": 11645333,
      "RevitName": "物流中心 五層天花平面圖(7/8)",
      "CurrentNumber": "ARB-D07101",
      "TargetNumber": "ARB-D07100"
    },
    {
      "Id": 11645563,
      "RevitName": "物流中心 五層天花平面圖(8/8)",
      "CurrentNumber": "ARB-D07102",
      "TargetNumber": "ARB-D07101"
    },
    {
      "Id": 11957407,
      "RevitName": "物流中心 五層標誌平面圖(8/9)",
      "CurrentNumber": "ARB-D07162",
      "TargetNumber": "ARB-D07164"
    },
    {
      "Id": 11204441,
      "RevitName": "物流中心 屋突層標誌平面圖",
      "CurrentNumber": "ARB-D07164",
      "TargetNumber": "ARB-D07166"
    },
    {
      "Id": 11633058,
      "RevitName": "物流中心 五層夾層天花平面圖(1/9)",
      "CurrentNumber": "ARB-D2XX261",
      "TargetNumber": "ARB-D07102"
    },
    {
      "Id": 11633800,
      "RevitName": "物流中心 五層夾層天花平面圖(2/9)",
      "CurrentNumber": "ARB-D2XX262",
      "TargetNumber": "ARB-D07103"
    },
    {
      "Id": 11634329,
      "RevitName": "物流中心 五層夾層天花平面圖(3/9)",
      "CurrentNumber": "ARB-D2XX263",
      "TargetNumber": "ARB-D07104"
    },
    {
      "Id": 11636017,
      "RevitName": "物流中心 五層夾層天花平面圖(4/9)",
      "CurrentNumber": "ARB-D2XX264",
      "TargetNumber": "ARB-D07105"
    },
    {
      "Id": 11636697,
      "RevitName": "物流中心 五層夾層天花平面圖(5/9)",
      "CurrentNumber": "ARB-D2XX265",
      "TargetNumber": "ARB-D07106"
    },
    {
      "Id": 11637513,
      "RevitName": "物流中心 五層夾層天花平面圖(6/9)",
      "CurrentNumber": "ARB-D2XX266",
      "TargetNumber": "ARB-D07107"
    },
    {
      "Id": 11638428,
      "RevitName": "物流中心 五層夾層天花平面圖(7/9)",
      "CurrentNumber": "ARB-D2XX267",
      "TargetNumber": "ARB-D07108"
    },
    {
      "Id": 11639272,
      "RevitName": "物流中心 五層夾層天花平面圖(8/9)",
      "CurrentNumber": "ARB-D2XX268",
      "TargetNumber": "ARB-D07109"
    },
    {
      "Id": 11640523,
      "RevitName": "物流中心 五層夾層天花平面圖(9/9)",
      "CurrentNumber": "ARB-D2XX269",
      "TargetNumber": "ARB-D07110"
    }
  ]
}